tracdiscussion/__init__.py
tracdiscussion/admin.py
tracdiscussion/ajax.py
tracdiscussion/api.py
tracdiscussion/core.py
tracdiscussion/init.py
tracdiscussion/model.py
tracdiscussion/notification.py
tracdiscussion/spamfilter.py
tracdiscussion/tags.py
tracdiscussion/timeline.py
tracdiscussion/util.py
tracdiscussion/wiki.py
tracdiscussion/db/__init__.py
tracdiscussion/db/db1.py
tracdiscussion/db/db2.py
tracdiscussion/db/db3.py
tracdiscussion/db/db4.py
tracdiscussion/db/db5.py
tracdiscussion/htdocs/solved.png
tracdiscussion/htdocs/unsolved.png
tracdiscussion/htdocs/css/admin.css
tracdiscussion/htdocs/css/discussion.css
tracdiscussion/htdocs/js/discussion.js
tracdiscussion/templates/admin-forum-list.html
tracdiscussion/templates/admin-group-list.html
tracdiscussion/templates/discussion-footer.html
tracdiscussion/templates/discussion-header.html
tracdiscussion/templates/discussion-macros.html
tracdiscussion/templates/forum-add.html
tracdiscussion/templates/forum-invite-body.txt
tracdiscussion/templates/forum-invite-subject.txt
tracdiscussion/templates/forum-list.html
tracdiscussion/templates/forum-subscribe.html
tracdiscussion/templates/forum-unsubscribe.html
tracdiscussion/templates/forum.rss
tracdiscussion/templates/message-list.html
tracdiscussion/templates/message-notify-body.txt
tracdiscussion/templates/message-notify-subject.txt
tracdiscussion/templates/topic-add.html
tracdiscussion/templates/topic-edit-attribute.html
tracdiscussion/templates/topic-invite-body.txt
tracdiscussion/templates/topic-invite-subject.txt
tracdiscussion/templates/topic-list-classic.html
tracdiscussion/templates/topic-list-compact.html
tracdiscussion/templates/topic-list.html
tracdiscussion/templates/topic-move.html
tracdiscussion/templates/topic-notify-body.txt
tracdiscussion/templates/topic-notify-subject.txt
tracdiscussion/templates/topic-subscribe.html
tracdiscussion/templates/topic-unsubscribe.html
tracdiscussion/templates/topic.rss
tracdiscussion/templates/wiki-discussion-denied.html
TracDiscussion-1.2.1.dist-info/COPYING
TracDiscussion-1.2.1.dist-info/METADATA
TracDiscussion-1.2.1.dist-info/WHEEL
TracDiscussion-1.2.1.dist-info/entry_points.txt
TracDiscussion-1.2.1.dist-info/top_level.txt
TracDiscussion-1.2.1.dist-info/RECORD
